duplicates/__init__.py
duplicates/bufferediofile.py
duplicates/cli.py
duplicates/dupes.py
link_duplicates-1.1.0.dist-info/METADATA
link_duplicates-1.1.0.dist-info/WHEEL
link_duplicates-1.1.0.dist-info/entry_points.txt
link_duplicates-1.1.0.dist-info/top_level.txt
link_duplicates-1.1.0.dist-info/RECORD
